pysampic/Dataset.py
pysampic/__init__.py
pysampic/datastructs.py
pysampic-0.1.dist-info/DESCRIPTION.rst
pysampic-0.1.dist-info/METADATA
pysampic-0.1.dist-info/RECORD
pysampic-0.1.dist-info/WHEEL
pysampic-0.1.dist-info/metadata.json
pysampic-0.1.dist-info/top_level.txt
