Metadata-Version: 2.0
Name: pysampic
Version: 0.1
Summary: Python decoder for the binary SAMPIC files
Home-page: https://gitlab.cern.ch/landerli/sampic_decoder
Author: Lucio Anderlini, Nicola Minafra
Author-email: lucio.anderlini@fi.infn.it
License: UNKNOWN
Platform: UNKNOWN
Classifier: Programming Language :: Python :: 3
Classifier: License :: OSI Approved :: MIT License
Classifier: Operating System :: OS Independent
